hf_tcr/__init__.py
hf_tcr/adapter.py
hf_tcr/constants.py
hf_tcr/evaluation.py
hf_tcr/tokenizer.py
hf_tcr/assets/tcrbart_merges.txt
hf_tcr/assets/tcrbart_vocab.json
hf_tcr/assets/tcrt5_tokenizer.model
hf_tcr-0.2.1.dist-info/LICENSE
hf_tcr-0.2.1.dist-info/METADATA
hf_tcr-0.2.1.dist-info/WHEEL
hf_tcr-0.2.1.dist-info/top_level.txt
hf_tcr-0.2.1.dist-info/RECORD
