Metadata-Version: 2.2
Name: hf-tcr
Version: 0.2.1
Summary: HuggingFace-based inference and evaluation library for TCR-pMHC sequence translation models
Author: Dhuvi Karthikeyan
License: Apache-2.0
Project-URL: Homepage, https://github.com/pirl-unc/hf-tcr
Project-URL: Documentation, https://github.com/pirl-unc/hf-tcr#readme
Project-URL: Repository, https://github.com/pirl-unc/hf-tcr
Project-URL: Issues, https://github.com/pirl-unc/hf-tcr/issues
Keywords: TCR,pMHC,immunology,machine-learning,transformers,huggingface,sequence-translation
Classifier: Development Status :: 4 - Beta
Classifier: Intended Audience :: Science/Research
Classifier: License :: OSI Approved :: Apache Software License
Classifier: Operating System :: OS Independent
Classifier: Programming Language :: Python :: 3
Classifier: Programming Language :: Python :: 3.9
Classifier: Programming Language :: Python :: 3.10
Classifier: Programming Language :: Python :: 3.11
Classifier: Programming Language :: Python :: 3.12
Classifier: Topic :: Scientific/Engineering :: Bio-Informatics
Classifier: Topic :: Scientific/Engineering :: Artificial Intelligence
Requires-Python: >=3.9
License-File: LICENSE
Requires-Dist: torch>=2.0.0
Requires-Dist: transformers>=4.30.0
Requires-Dist: numpy>=1.21.0
Requires-Dist: pandas>=1.3.0
Requires-Dist: tqdm>=4.60.0
Requires-Dist: python-Levenshtein>=0.20.0
Requires-Dist: nltk>=3.7
Requires-Dist: einops>=0.6.0
Requires-Dist: tidytcells>=2.0.0
Requires-Dist: mhcgnomes>=1.8.0
Requires-Dist: tcrpmhcdataset>=0.2.0
Provides-Extra: dev
Requires-Dist: pytest>=7.0.0; extra == "dev"
Requires-Dist: pytest-cov>=4.0.0; extra == "dev"
Requires-Dist: black>=23.0.0; extra == "dev"
Requires-Dist: ruff>=0.1.0; extra == "dev"
